{
  "products": [
    {
      "id": 10,
      "name": "Egg",
      "category": "Food",
      "isAvailable": true,
      "price": 5
    },
    {
      "id": 7,
      "name": "Windows",
      "category": "Software",
      "isAvailable": true,
      "price": 500
    },
    {
      "id": 1960,
      "name": "Zaporozhec",
      "category": "Car",
      "isAvailable": false,
      "price": 15.65
    },
    {
      "id": 8,
      "name": "Icecream",
      "category": "Food",
      "isAvailable": true,
      "price": 12.2
    },
    {
      "id": 100,
      "name": "AlphaZero",
      "category": "Software",
      "isAvailable": false,
      "price": 150000
    },
    {
      "id": 120,
      "name": "lower-case item",
      "category": "Software",
      "isAvailable": false,
      "price": 150000
    }
  ],
  "cart": {
    "products": [
      {
        "product": {
          "id": 7,
          "name": "Windows",
          "category": "Software",
          "isAvailable": true,
          "price": 500
        },
        "amount": 5,
        "added": "2021-10-28T19:18:06.750Z"
      },
      {
        "product": {
          "id": 8,
          "name": "Icecream",
          "category": "Food",
          "isAvailable": true,
          "price": 12.2
        },
        "amount": 2,
        "added": "2021-10-28T19:18:30.845Z"
      }
    ],
    "quantity": 7,
    "sum": 2524.4
  },
  "users": [
    {
      "id": 1,
      "name": "Mr. White"
    }
  ]
}